dstree/__init__.py
dstree/backend.py
dstree/feature_dataset_example.pkl
dstree/front.py
dstree/train_data.csv
dstree/wos-v1.pkl
dstree/woz_train_en.json
dstree-3.4.dist-info/METADATA
dstree-3.4.dist-info/WHEEL
dstree-3.4.dist-info/top_level.txt
dstree-3.4.dist-info/RECORD
