Metadata-Version: 2.1
Name: dstree
Version: 3.4
Summary: A module for visualization of a nested python data structure
Home-page: UNKNOWN
Author: datadriven42
Author-email: datadriven42@gmail.com
License: MIT
Platform: UNKNOWN
Classifier: Programming Language :: Python :: 3
Classifier: License :: OSI Approved :: MIT License
Classifier: Operating System :: OS Independent
Requires-Python: >=3.6
Requires-Dist: numpy
Requires-Dist: torch
Requires-Dist: treelib
Requires-Dist: pandas
Requires-Dist: graphviz
Requires-Dist: sklearn
Requires-Dist: dill
